l4py/__init__.py
l4py/builder.py
l4py/formatters.py
l4py/utils.py
l4py-0.1.9.dist-info/LICENSE
l4py-0.1.9.dist-info/METADATA
l4py-0.1.9.dist-info/WHEEL
l4py-0.1.9.dist-info/top_level.txt
l4py-0.1.9.dist-info/RECORD
