Metadata-Version: 2.1
Name: l4py
Version: 0.1.9
Summary: l4py is a Python library that simplifies logging configuration with features like JSON formatting, file rotation, and dynamic log levels via environment variables. It integrates seamlessly with Django and leverages the Python standard logging module for easy customization.
Home-page: https://github.com/roymanigley/l4py
Author: Roy Manigley
Author-email: roy.manigley@gmail.com
License: MIT
Classifier: Development Status :: 5 - Production/Stable
Classifier: Intended Audience :: Developers
Classifier: License :: OSI Approved :: MIT License
Classifier: Operating System :: POSIX :: Linux
Classifier: Programming Language :: Python :: 3.11
License-File: LICENSE
